{
  "asof": "21 July 2026",
  "cards": [
    {
      "slug": "total",
      "figure": "\u00a3131,953,750,506",
      "label": "paid in direct, measured subsidy to renewable electricity generators since 2002, in today\u2019s money",
      "png": "/share/total.png?v=912342a8b6",
      "group": "Headline figures",
      "scope": "direct"
    },
    {
      "slug": "run-rate",
      "figure": "\u00a312,315,142,486",
      "label": "a year \u2014 the current run-rate of direct subsidy to renewable generators, in today\u2019s money",
      "png": "/share/run-rate.png?v=32a5f39d71",
      "group": "Headline figures",
      "scope": "direct"
    },
    {
      "slug": "household",
      "figure": "\u00a3424.66",
      "label": "per household per year in direct subsidy to renewable generators, in today\u2019s money",
      "png": "/share/household.png?v=7b88e1da85",
      "group": "Headline figures",
      "scope": "direct"
    },
    {
      "slug": "per-mwh",
      "figure": "\u00a344.97",
      "label": "of direct subsidy on every MWh of electricity delivered in the UK, in today\u2019s money",
      "png": "/share/per-mwh.png?v=ac2355dcf8",
      "group": "Headline figures",
      "scope": "direct"
    },
    {
      "slug": "headline",
      "figure": "\u00a3228,091,915,290",
      "label": "the full cost of subsidising UK renewables since 2002, including estimated indirect costs, in today\u2019s money",
      "png": "/share/headline.png?v=3fdfeb1e6a",
      "group": "Headline figures",
      "scope": "full"
    },
    {
      "slug": "run-rate-full",
      "figure": "\u00a320,027,158,843",
      "label": "a year \u2014 the full cost of UK renewable subsidy including estimated indirect costs, in today\u2019s money",
      "png": "/share/run-rate-full.png?v=9d112d0d4e",
      "group": "Headline figures",
      "scope": "full"
    },
    {
      "slug": "household-full",
      "figure": "\u00a3690.59",
      "label": "per household per year in subsidy to renewable generators \u2014 the full cost including estimated indirect costs, in today\u2019s money",
      "png": "/share/household-full.png?v=9237f45bf2",
      "group": "Headline figures",
      "scope": "full"
    },
    {
      "slug": "per-mwh-full",
      "figure": "\u00a373.13",
      "label": "on every MWh of electricity delivered \u2014 the full cost including estimated indirect costs, in today\u2019s money",
      "png": "/share/per-mwh-full.png?v=8ccffd88c3",
      "group": "Headline figures",
      "scope": "full"
    },
    {
      "slug": "the-bill",
      "figure": "\u00a3228,091,915,290",
      "label": "the cumulative cost of direct and estimated indirect subsidy to renewables since 2002, in today\u2019s money",
      "png": "/share/the-bill.png?v=2eec6b24e6",
      "group": "Headline figures",
      "scope": "graph"
    },
    {
      "slug": "switch-off",
      "figure": "\u00a32,848,484,865",
      "label": "paid to wind farms to reduce output when the grid could not carry their electricity, since 2010, in today\u2019s money",
      "png": "/share/switch-off.png?v=54ce20f720",
      "group": "Direct schemes",
      "scope": null
    },
    {
      "slug": "renewables-obligation",
      "figure": "\u00a392,325,705,597",
      "label": "Renewables Obligation \u2014 cumulative cost since 2002, in today\u2019s money",
      "png": "/share/renewables-obligation.png?v=3f9e40060c",
      "group": "Direct schemes",
      "scope": null
    },
    {
      "slug": "feed-in-tariffs",
      "figure": "\u00a322,002,642,909",
      "label": "Feed-in Tariffs \u2014 cumulative cost since 2010, in today\u2019s money",
      "png": "/share/feed-in-tariffs.png?v=76c625494e",
      "group": "Direct schemes",
      "scope": null
    },
    {
      "slug": "contracts-for-difference",
      "figure": "\u00a314,776,917,133",
      "label": "Contracts for Difference \u2014 cumulative cost since 2016, in today\u2019s money",
      "png": "/share/contracts-for-difference.png?v=09cddd1e1f",
      "group": "Direct schemes",
      "scope": null
    },
    {
      "slug": "capacity-market",
      "figure": "\u00a39,590,128,716",
      "label": "Capacity Market \u2014 cumulative cost since 2016, estimated, in today\u2019s money",
      "png": "/share/capacity-market.png?v=758bec20bc",
      "group": "Indirect schemes (estimated)",
      "scope": null
    },
    {
      "slug": "climate-change-levy",
      "figure": "\u00a329,976,546,811",
      "label": "Climate Change Levy \u2014 cumulative cost since 2002, estimated, in today\u2019s money",
      "png": "/share/climate-change-levy.png?v=ffe08351ce",
      "group": "Indirect schemes (estimated)",
      "scope": null
    },
    {
      "slug": "bsuos",
      "figure": "\u00a314,856,899,582",
      "label": "Balancing the grid (BSUoS) \u2014 cumulative cost since 2002, estimated, in today\u2019s money",
      "png": "/share/bsuos.png?v=c9667e67dd",
      "group": "Indirect schemes (estimated)",
      "scope": null
    },
    {
      "slug": "emissions-trading",
      "figure": "\u00a312,277,756,195",
      "label": "Emissions trading \u2014 cumulative cost since 2009, estimated, in today\u2019s money",
      "png": "/share/emissions-trading.png?v=0c59c27c88",
      "group": "Indirect schemes (estimated)",
      "scope": null
    },
    {
      "slug": "tnuos",
      "figure": "\u00a329,436,833,478",
      "label": "Grid upgrades for renewables (TNUoS) \u2014 cumulative cost since 2002, estimated, in today\u2019s money",
      "png": "/share/tnuos.png?v=3bdbfa4962",
      "group": "Indirect schemes (estimated)",
      "scope": null
    },
    {
      "slug": "nurses",
      "figure": "315,000",
      "label": "NHS nurses' annual salaries paid by one year of direct renewable subsidy, in today's money",
      "png": "/share/nurses.png?v=1081b7f243",
      "group": "What it could have bought",
      "scope": null
    },
    {
      "slug": "homes",
      "figure": "559,000",
      "label": "social homes (land included) the current \u00a3220bn+ full UK renewables cost would have built, in today's money",
      "png": "/share/homes.png?v=7bcb18d320",
      "group": "What it could have bought",
      "scope": null
    },
    {
      "slug": "hinkley",
      "figure": "4",
      "label": "Hinkley Point C-scale nuclear stations the current \u00a3220bn+ full UK renewables cost would have built, in today's money",
      "png": "/share/hinkley.png?v=8a11321a9b",
      "group": "What it could have bought",
      "scope": null
    },
    {
      "slug": "secondary-schools",
      "figure": "4,400",
      "label": "large new secondary schools the current \u00a3220bn+ full UK renewables cost would have built, in today's money",
      "png": "/share/secondary-schools.png?v=06f6a8c23d",
      "group": "What it could have bought",
      "scope": null
    },
    {
      "slug": "hospitals",
      "figure": "110",
      "label": "the largest new NHS hospitals the current \u00a3220bn+ full UK renewables cost would have built, in today's money",
      "png": "/share/hospitals.png?v=1e353835f5",
      "group": "What it could have bought",
      "scope": null
    },
    {
      "slug": "aircraft-carriers",
      "figure": "53",
      "label": "Queen Elizabeth-class aircraft carriers the current \u00a3220bn+ full UK renewables cost would have built, in today's money",
      "png": "/share/aircraft-carriers.png?v=5de9cc6b78",
      "group": "What it could have bought",
      "scope": null
    },
    {
      "slug": "crossrail",
      "figure": "10",
      "label": "Crossrail / Elizabeth Lines the current \u00a3220bn+ full UK renewables cost would have built, in today's money",
      "png": "/share/crossrail.png?v=d09bc55258",
      "group": "What it could have bought",
      "scope": null
    },
    {
      "slug": "stadiums",
      "figure": "220",
      "label": "billion-pound football stadiums the current \u00a3220bn+ full UK renewables cost would have built, in today's money",
      "png": "/share/stadiums.png?v=037bdd88f8",
      "group": "What it could have bought",
      "scope": null
    },
    {
      "slug": "teachers",
      "figure": "241,000",
      "label": "experienced schoolteachers' annual salaries paid by one year of UK renewable subsidy, in today's money",
      "png": "/share/teachers.png?v=cf18d62e59",
      "group": "What it could have bought",
      "scope": null
    },
    {
      "slug": "police",
      "figure": "245,000",
      "label": "police officers' annual salaries paid by one year of UK renewable subsidy, in today's money",
      "png": "/share/police.png?v=7334bcda00",
      "group": "What it could have bought",
      "scope": null
    },
    {
      "slug": "free-school-meals",
      "figure": "2",
      "label": "years of free school meals for every UK schoolchild, funded by one year of UK renewable subsidy, in today's money",
      "png": "/share/free-school-meals.png?v=99587fc590",
      "group": "What it could have bought",
      "scope": null
    }
  ]
}